acanthophis/__init__.py
acanthophis/_version.py
acanthophis/cmd.py
acanthophis/template/config.yml
acanthophis/template/environment.yml
acanthophis/template/rawdata/adapters.txt
acanthophis/template/rawdata/nextera.txt
acanthophis/template/workflow/Snakefile
acanthophis/template/workflow/config.schema.yml
acanthophis/template/workflow/profiles/cobra.mpcdf/README.md
acanthophis/template/workflow/profiles/cobra.mpcdf/cluster.yml
acanthophis/template/workflow/profiles/cobra.mpcdf/config.yaml
acanthophis/template/workflow/profiles/cobra.mpcdf/jobscript.sh
acanthophis/template/workflow/profiles/cobra.mpcdf/jobstatus
acanthophis/template/workflow/profiles/cobra.mpcdf/jobsubmit
acanthophis/template/workflow/profiles/cobra.mpcdf/resources.yml
acanthophis/template/workflow/profiles/cobra.mpcdf/submit.sh
acanthophis/template/workflow/profiles/ebio-cluster/README.md
acanthophis/template/workflow/profiles/ebio-cluster/cluster.yml
acanthophis/template/workflow/profiles/ebio-cluster/config.yaml
acanthophis/template/workflow/profiles/ebio-cluster/jobscript.sh
acanthophis/template/workflow/profiles/ebio-cluster/jobstatus
acanthophis/template/workflow/profiles/ebio-cluster/jobsubmit
acanthophis/template/workflow/profiles/ebio-cluster/resources.yml
acanthophis/template/workflow/profiles/ebio-cluster/run.job
acanthophis/template/workflow/profiles/ebio-cluster/submit.sh
acanthophis/template/workflow/profiles/ebio-cluster-semilocal/README.md
acanthophis/template/workflow/profiles/ebio-cluster-semilocal/cluster.yml
acanthophis/template/workflow/profiles/ebio-cluster-semilocal/config.yaml
acanthophis/template/workflow/profiles/ebio-cluster-semilocal/jobscript.sh
acanthophis/template/workflow/profiles/ebio-cluster-semilocal/jobstatus
acanthophis/template/workflow/profiles/ebio-cluster-semilocal/jobsubmit
acanthophis/template/workflow/profiles/ebio-cluster-semilocal/resources.yml
acanthophis/template/workflow/profiles/ebio-cluster-semilocal/run.job
acanthophis-1.1.0.dist-info/LICENSE
acanthophis-1.1.0.dist-info/METADATA
acanthophis-1.1.0.dist-info/WHEEL
acanthophis-1.1.0.dist-info/entry_points.txt
acanthophis-1.1.0.dist-info/top_level.txt
acanthophis-1.1.0.dist-info/RECORD
