Metadata-Version: 2.1
Name: acanthophis
Version: 1.1.0
Summary: A comprehensive, opinionated plant variant calling pipeline in Snakemake
Home-page: https://github.com/kdm9/acanthophis
Author: Dr. K. D. Murray
Author-email: foss@kdmurray.id.au
Project-URL: Bug Tracker, https://github.com/kdm9/acanthophis/issues
Project-URL: Source, https://github.com/kdm9/acanthophis
Classifier: Development Status :: 4 - Beta
Classifier: Environment :: Console
Classifier: Intended Audience :: Science/Research
Classifier: License :: OSI Approved :: Mozilla Public License 2.0 (MPL 2.0)
Classifier: Operating System :: OS Independent
Classifier: Programming Language :: Python :: 3
Classifier: Programming Language :: Unix Shell
Classifier: Topic :: Scientific/Engineering :: Bio-Informatics
License-File: LICENSE
Requires-Dist: natsort
Requires-Dist: snakemake>=8
